oligo/__init__.py
oligo/__main__.py
oligo/cmdline/commands.py
oligo/cmdline/wrappers.py
oligo/design.py
oligo/tools.py
oligo_capture-0.2.0.dist-info/LICENSE.md
oligo_capture-0.2.0.dist-info/METADATA
oligo_capture-0.2.0.dist-info/WHEEL
oligo_capture-0.2.0.dist-info/RECORD
