Metadata-Version: 2.1
Name: oligo-capture
Version: 0.2.0
Summary: A tool for designing oligos for DNA capture
Home-page: https://github.com/jbkerry/oligo
License: GPL-3.0-only
Author: Jon Kerry
Author-email: jonbkerry@gmail.com
Requires-Python: >=3.8,<4.0
Classifier: License :: OSI Approved :: GNU General Public License v3 (GPLv3)
Classifier: Programming Language :: Python :: 3
Classifier: Programming Language :: Python :: 3.8
Classifier: Programming Language :: Python :: 3.9
Classifier: Programming Language :: Python :: 3.10
Classifier: Programming Language :: Python :: 3.11
Requires-Dist: biopython (>=1.60,<2.0)
Requires-Dist: click (>=8.1.6,<9.0.0)
Requires-Dist: h5py (>=3.9.0,<4.0.0)
Requires-Dist: numpy (>=1.21.0,<2.0.0)
Requires-Dist: pandas (>=2.0.0,<3.0.0)
Requires-Dist: pysam (>=0.21.0,<0.22.0)
Project-URL: Documentation, https://oligo.readthedocs.io/
Project-URL: Repository, https://github.com/jbkerry/oligo
